{
    "results": {
        "Calcium_chloride_hydroxide_24403-icsd": {
            "RWP": 0.0,
            "percentage_weight": null,
            "crystallite_size": 3.89082075
        },
        "Arcanite": {
            "RWP": 0.0,
            "percentage_weight": 0.322,
            "crystallite_size": 1055.32233
        },
        "Yeelimite_9009938": {
            "RWP": 0.0,
            "percentage_weight": null,
            "crystallite_size": 7.280789458241546e+16
        },
        "Hydrocalumite": {
            "RWP": 0.0,
            "percentage_weight": 3.787,
            "crystallite_size": 50.0
        },
        "rwp_all": {
            "RWP": 10.1288294,
            "percentage_weight": null,
            "crystallite_size": null
        },
        "Sylvite": {
            "RWP": 0.0,
            "percentage_weight": 1.619,
            "crystallite_size": 234.32607
        },
        "MicroInt1": {
            "RWP": 0.0,
            "percentage_weight": 1.198,
            "crystallite_size": 262.44499
        },
        "Gypsum": {
            "RWP": 0.0,
            "percentage_weight": 0.321,
            "crystallite_size": 50.0
        },
        "C3A-Na-cubic": {
            "RWP": 0.0,
            "percentage_weight": 0.837,
            "crystallite_size": 45.0
        },
        "Calcite": {
            "RWP": 0.0,
            "percentage_weight": 40.749,
            "crystallite_size": 61.33854
        },
        "Quartz": {
            "RWP": 0.0,
            "percentage_weight": 5.298,
            "crystallite_size": 219.81395
        },
        "Dolomite": {
            "RWP": 0.0,
            "percentage_weight": 0.619,
            "crystallite_size": 50.0
        },
        "Albint": {
            "RWP": 0.0,
            "percentage_weight": 1.53,
            "crystallite_size": 50.00001
        },
        "Larnite": {
            "RWP": 0.0,
            "percentage_weight": 2.425,
            "crystallite_size": 50.0
        },
        "C3S-tric_belov": {
            "RWP": 0.0,
            "percentage_weight": 1.803,
            "crystallite_size": 136.85021
        },
        "C3S-mono_nishi": {
            "RWP": -0.049430289545601545,
            "percentage_weight": 0.792,
            "crystallite_size": 246.10635
        },
        "C3S3H-Rosenhahnite": {
            "RWP": -0.031772033794941805,
            "percentage_weight": 1.067,
            "crystallite_size": 147.51881
        },
        "Syngenite": {
            "RWP": 0.0,
            "percentage_weight": 2.688,
            "crystallite_size": 50.0
        },
        "Portlandite": {
            "RWP": 0.0,
            "percentage_weight": 5.053,
            "crystallite_size": 56.37559
        },
        "Vaterite": {
            "RWP": -0.0272178540197351,
            "percentage_weight": 0.708,
            "crystallite_size": 50.0
        },
        "Aragonit": {
            "RWP": -0.022931461359197276,
            "percentage_weight": 0.357,
            "crystallite_size": 81.95885
        },
        "Aphthita": {
            "RWP": 0.023320819284408125,
            "percentage_weight": 0.643,
            "crystallite_size": 50.05624
        },
        "Zro2mkl": {
            "RWP": -0.0010958719474534128,
            "percentage_weight": 0.688,
            "crystallite_size": 50.06814
        },
        "LangbeiniteDipotassium_dicalcium_tris(sulfate(VI))_40989-icsd": {
            "RWP": 0.0,
            "percentage_weight": 0.528,
            "crystallite_size": 50.00001
        },
        "Thaumasite": {
            "RWP": 0.0,
            "percentage_weight": 0.485,
            "crystallite_size": 320.80828
        },
        "Ettringite-from-CIF-good": {
            "RWP": -0.02356255106833965,
            "percentage_weight": 0.139,
            "crystallite_size": 1999.84107
        },
        "C2S-apha_mumme": {
            "RWP": -0.04046577485054692,
            "percentage_weight": 0.466,
            "crystallite_size": 2.5036966530789802e+17
        },
        "Corundum as standard": {
            "RWP": 0.0,
            "percentage_weight": 29.577,
            "crystallite_size": 282.37742
        },
        "Phillips": {
            "RWP": 0.0,
            "percentage_weight": 0.688,
            "crystallite_size": 50.00001
        },
        "Gehlenite": {
            "RWP": -0.008870383383098675,
            "percentage_weight": 0.972,
            "crystallite_size": 50.3643
        },
        "Magnetite": {
            "RWP": 0.0,
            "percentage_weight": 0.231,
            "crystallite_size": 188.54303
        },
        "C2SH-alpha": {
            "RWP": 0.0,
            "percentage_weight": 0.244,
            "crystallite_size": 1999.47579
        },
        "initial_structure_list": [
            "Calcium_chloride_hydroxide_24403-icsd",
            "Arcanite",
            "Yeelimite_9009938",
            "Hydrocalumite",
            "Sylvite",
            "MicroInt1",
            "Gypsum",
            "C3A-Na-cubic",
            "Calcite",
            "Quartz",
            "Dolomite",
            "Albint",
            "Larnite",
            "C3S-tric_belov",
            "Syngenite",
            "Portlandite",
            "LangbeiniteDipotassium_dicalcium_tris(sulfate(VI))_40989-icsd",
            "Thaumasite",
            "Corundum as standard",
            "Phillips",
            "Magnetite",
            "C2SH-alpha",
            "C3S-mono_nishi",
            "C3S3H-Rosenhahnite",
            "Vaterite",
            "Aragonit",
            "Aphthita",
            "Zro2mkl",
            "Ettringite-from-CIF-good",
            "C2S-apha_mumme",
            "Gehlenite"
        ],
        "final_structure_list": [
            "Calcium_chloride_hydroxide_24403-icsd.str",
            "Arcanite.str",
            "Yeelimite_9009938.str",
            "Hydrocalumite.str",
            "Sylvite.str",
            "MicroInt1.str",
            "Gypsum.str",
            "C3A-Na-cubic.str",
            "Calcite.str",
            "Quartz.str",
            "Dolomite.str",
            "Albint.str",
            "Larnite.str",
            "C3S-tric_belov.str",
            "Syngenite.str",
            "Portlandite.str",
            "LangbeiniteDipotassium_dicalcium_tris(sulfate(VI))_40989-icsd.str",
            "Thaumasite.str",
            "Corundum as standard.str",
            "Phillips.str",
            "Magnetite.str",
            "C2SH-alpha.str",
            "C3S-mono_nishi.str",
            "C3S3H-Rosenhahnite.str"
        ],
        "structures_list": [
            "Calcium_chloride_hydroxide_24403-icsd.str",
            "Arcanite.str",
            "Yeelimite_9009938.str",
            "Hydrocalumite.str",
            "Sylvite.str",
            "MicroInt1.str",
            "Gypsum.str",
            "C3A-Na-cubic.str",
            "Calcite.str",
            "Quartz.str",
            "Dolomite.str",
            "Albint.str",
            "Larnite.str",
            "C3S-tric_belov.str",
            "Syngenite.str",
            "Portlandite.str",
            "LangbeiniteDipotassium_dicalcium_tris(sulfate(VI))_40989-icsd.str",
            "Thaumasite.str",
            "Corundum as standard.str",
            "Phillips.str",
            "Magnetite.str",
            "C2SH-alpha.str",
            "C3S-mono_nishi.str",
            "C3S3H-Rosenhahnite.str"
        ]
    },
    "valid_structures": [
        "Calcium_chloride_hydroxide_24403-icsd",
        "Arcanite",
        "Yeelimite_9009938",
        "Hydrocalumite",
        "Sylvite",
        "MicroInt1",
        "Gypsum",
        "C3A-Na-cubic",
        "Calcite",
        "Quartz",
        "Dolomite",
        "Albint",
        "Larnite",
        "C3S-tric_belov",
        "Syngenite",
        "Portlandite",
        "LangbeiniteDipotassium_dicalcium_tris(sulfate(VI))_40989-icsd",
        "Thaumasite",
        "Corundum as standard",
        "Phillips",
        "Magnetite",
        "C2SH-alpha"
    ],
    "invalid_structures": [
        "C3S-mono_nishi",
        "C3S3H-Rosenhahnite",
        "Vaterite",
        "Aragonit",
        "Aphthita",
        "Zro2mkl",
        "Ettringite-from-CIF-good",
        "C2S-apha_mumme",
        "Gehlenite"
    ],
    "structures_list": [
        "Calcium_chloride_hydroxide_24403-icsd.str",
        "Arcanite.str",
        "Yeelimite_9009938.str",
        "Hydrocalumite.str",
        "Sylvite.str",
        "MicroInt1.str",
        "Gypsum.str",
        "C3A-Na-cubic.str",
        "Calcite.str",
        "Quartz.str",
        "Dolomite.str",
        "Albint.str",
        "Larnite.str",
        "C3S-tric_belov.str",
        "Syngenite.str",
        "Portlandite.str",
        "LangbeiniteDipotassium_dicalcium_tris(sulfate(VI))_40989-icsd.str",
        "Thaumasite.str",
        "Corundum as standard.str",
        "Phillips.str",
        "Magnetite.str",
        "C2SH-alpha.str",
        "C3S-mono_nishi.str",
        "C3S3H-Rosenhahnite.str"
    ],
    "excluded_structure_list": [
        "Gehlenite",
        "Vaterite",
        "C2S-apha_mumme",
        "Zro2mkl",
        "Aragonit",
        "Ettringite-from-CIF-good",
        "Aphthita"
    ],
    "iteration": 1
}